sqltail/__init__.py
sqltail/cli.py
sqltail/db.py
sqltail/monitor.py
sqltail-1.0.3.dist-info/LICENSE
sqltail-1.0.3.dist-info/METADATA
sqltail-1.0.3.dist-info/WHEEL
sqltail-1.0.3.dist-info/entry_points.txt
sqltail-1.0.3.dist-info/top_level.txt
sqltail-1.0.3.dist-info/RECORD
