Metadata-Version: 2.1
Name: sqltail
Version: 1.0.3
Summary: SQL Query Tail
Home-page: UNKNOWN
License: MIT
Platform: UNKNOWN
Requires-Python: >=3.6
Requires-Dist: arrow
Requires-Dist: click
Requires-Dist: dotmap
Requires-Dist: mysql-connector
Requires-Dist: bumpversion
Provides-Extra: test
Requires-Dist: pytest ; extra == 'test'
Requires-Dist: pytest-click ; extra == 'test'
